lazy_load/__init__.py
lazy_load/_lazy_load.py
lazy_load-0.8.3.dist-info/LICENSE
lazy_load-0.8.3.dist-info/METADATA
lazy_load-0.8.3.dist-info/WHEEL
lazy_load-0.8.3.dist-info/top_level.txt
lazy_load-0.8.3.dist-info/RECORD
