Metadata-Version: 2.1
Name: lazy-load
Version: 0.8.3
Summary: ℒazy-ℒoad - A minimalistic interface that allows the lazy evaluation of expressions. Additional functions and wrappers allow it to easily use the lazy evaluation for functions and classes.
Home-page: https://github.com/kutoga/lazy-load
Author: Benjamin Bruno Meier
Author-email: benjamin.meier70@gmail.com
License: MIT
Classifier: Development Status :: 2 - Pre-Alpha
Classifier: License :: OSI Approved :: MIT License
Classifier: Programming Language :: Python
Classifier: Programming Language :: Python :: 3.5
Classifier: Programming Language :: Python :: 3.6
Classifier: Programming Language :: Python :: 3.7
Classifier: Programming Language :: Python :: 3.8
Classifier: Programming Language :: Python :: 3.9
Classifier: Programming Language :: Python :: 3.10
Classifier: Programming Language :: Python :: 3.11
License-File: LICENSE
Requires-Dist: lazy-object-proxy (>=1.3.1)
